cocode_mcp-0.1.2.dist-info/METADATA
cocode_mcp-0.1.2.dist-info/WHEEL
cocode_mcp-0.1.2.dist-info/entry_points.txt
cocode_mcp-0.1.2.dist-info/licenses/LICENSE
cocode_rust/__init__.py
cocode_rust/cocode_rust.abi3.so
config/__init__.py
config/settings.py
src/__init__.py
src/embeddings/__init__.py
src/embeddings/backend.py
src/embeddings/http_client.py
src/embeddings/jina.py
src/embeddings/mistral.py
src/embeddings/openai.py
src/embeddings/provider.py
src/evaluation/__init__.py
src/evaluation/metrics.py
src/exceptions.py
src/indexer/__init__.py
src/indexer/call_graph_indexing.py
src/indexer/flow.py
src/indexer/repo_manager.py
src/indexer/service.py
src/indexer/symbol_indexing.py
src/models.py
src/monitoring/__init__.py
src/monitoring/metrics.py
src/parser/__init__.py
src/parser/ast_parser.py
src/parser/call_extractor.py
src/parser/symbol_extractor.py
src/retrieval/__init__.py
src/retrieval/bm25_search.py
src/retrieval/call_graph.py
src/retrieval/centrality.py
src/retrieval/curation.py
src/retrieval/dependencies.py
src/retrieval/embedding_cache.py
src/retrieval/file_categorizer.py
src/retrieval/fts_setup.py
src/retrieval/graph_cache.py
src/retrieval/graph_expansion.py
src/retrieval/hybrid.py
src/retrieval/reranker.py
src/retrieval/service.py
src/retrieval/symbol_categorizer.py
src/retrieval/symbol_implementation.py
src/retrieval/symbol_search.py
src/retrieval/tokenizer.py
src/retrieval/ttl_cache.py
src/retrieval/vector_search.py
src/rust_bridge/__init__.py
src/rust_bridge/bm25_engine.py
src/rust_bridge/graph_algos.py
src/rust_bridge/parser.py
src/rust_bridge/tokenizer.py
src/rust_bridge/utils.py
src/rust_bridge/vector_ops.py
src/server.py
src/storage/__init__.py
src/storage/postgres.py
src/storage/schema.py
cocode_mcp-0.1.2.dist-info/RECORD
