Metadata-Version: 2.4
Name: cocode-mcp
Version: 0.1.2
Classifier: Development Status :: 3 - Alpha
Classifier: Intended Audience :: Developers
Classifier: License :: OSI Approved :: MIT License
Classifier: Programming Language :: Python :: 3
Classifier: Programming Language :: Python :: 3.10
Classifier: Programming Language :: Python :: 3.11
Classifier: Programming Language :: Python :: 3.12
Classifier: Programming Language :: Rust
Classifier: Topic :: Software Development :: Libraries :: Python Modules
Classifier: Topic :: Scientific/Engineering :: Artificial Intelligence
Requires-Dist: fastmcp>=2.0
Requires-Dist: cocoindex>=0.3.0
Requires-Dist: openai>=1.0
Requires-Dist: cohere>=5.0
Requires-Dist: httpx>=0.24
Requires-Dist: psycopg[binary,pool]>=3.0
Requires-Dist: python-dotenv>=1.0
Requires-Dist: pathspec>=0.12
Requires-Dist: tree-sitter>=0.21.0
Requires-Dist: tree-sitter-python>=0.21.0
Requires-Dist: tree-sitter-go>=0.21.0
Requires-Dist: tree-sitter-rust>=0.21.0
Requires-Dist: tree-sitter-c>=0.21.0
Requires-Dist: tree-sitter-cpp>=0.21.0
Requires-Dist: tree-sitter-javascript>=0.21.0
Requires-Dist: tree-sitter-typescript>=0.21.0
Requires-Dist: pytest>=7.0 ; extra == 'dev'
Requires-Dist: pytest-asyncio>=0.21 ; extra == 'dev'
Requires-Dist: pytest-benchmark>=4.0 ; extra == 'dev'
Requires-Dist: maturin>=1.7 ; extra == 'dev'
Provides-Extra: dev
License-File: LICENSE
Summary: High-performance MCP server for semantic codebase search with hybrid retrieval (vector + BM25 + symbol search)
Keywords: mcp,model-context-protocol,code-search,semantic-search,codebase-indexing,vector-search,bm25
Author-email: hrayleung <hrayleung@users.noreply.github.com>
License: MIT
Requires-Python: >=3.10
Project-URL: Homepage, https://github.com/hrayleung/Cocode
Project-URL: Issues, https://github.com/hrayleung/Cocode/issues
Project-URL: Repository, https://github.com/hrayleung/Cocode
